nautobot_bulk_connect/__init__.py
nautobot_bulk_connect/forms.py
nautobot_bulk_connect/template_content.py
nautobot_bulk_connect/templates/nautobot_bulk_connect/cable_connect.html
nautobot_bulk_connect/templates/nautobot_bulk_connect/inc/buttons.html
nautobot_bulk_connect/urls.py
nautobot_bulk_connect/views.py
nautobot_bulk_connect-1.0.3.dist-info/LICENSE.txt
nautobot_bulk_connect-1.0.3.dist-info/METADATA
nautobot_bulk_connect-1.0.3.dist-info/WHEEL
nautobot_bulk_connect-1.0.3.dist-info/RECORD
