Metadata-Version: 2.3
Name: nautobot-bulk-connect
Version: 1.0.3
Summary: A Nautobot plugin for bulk connections
License: Apache-2.0
Author: Gesellschaft für wissenschaftliche Datenverarbeitung mbH Göttingen
Author-email: netzadmin@gwdg.de
Requires-Python: >=3.9,<3.13
Classifier: License :: OSI Approved :: Apache Software License
Classifier: Programming Language :: Python :: 3
Classifier: Programming Language :: Python :: 3.9
Classifier: Programming Language :: Python :: 3.10
Classifier: Programming Language :: Python :: 3.11
Classifier: Programming Language :: Python :: 3.12
Requires-Dist: nautobot (>=2.0.0,<3.0.0)
